jupymod/__init__.py
jupymod/server.py
jupymod-0.1.1.dist-info/METADATA
jupymod-0.1.1.dist-info/WHEEL
jupymod-0.1.1.dist-info/entry_points.txt
jupymod-0.1.1.dist-info/top_level.txt
jupymod-0.1.1.dist-info/RECORD
