Metadata-Version: 2.4
Name: jupymod
Version: 0.1.1
Summary: A Model Context Protocol server for Jupyter notebooks - you still need to run your code lol
Requires-Python: >=3.12
Requires-Dist: mcp[cli]>=1.9.1
Requires-Dist: ruff>=0.11.11
